kari/__init__.py
kari/kari.py
kari-1.0.1.dist-info/LICENSE
kari-1.0.1.dist-info/METADATA
kari-1.0.1.dist-info/WHEEL
kari-1.0.1.dist-info/top_level.txt
kari-1.0.1.dist-info/RECORD
