Metadata-Version: 2.1
Name: kari
Version: 1.0.1
Summary: Python logic to find the number
Home-page: UNKNOWN
Author: kari (Karthick Sundaram)
Author-email: <karthick.sundaram@hotmail.com>
License: UNKNOWN
Keywords: python,kari,mindreader
Platform: UNKNOWN
Classifier: Development Status :: 1 - Planning
Classifier: Intended Audience :: Developers
Classifier: Programming Language :: Python :: 3
Classifier: Operating System :: Unix
Classifier: Operating System :: MacOS :: MacOS X
Classifier: Operating System :: Microsoft :: Windows
